pycolors_kit/__init__.py
pycolors_kit/color.py
pycolors_kit-1.0.4.dist-info/METADATA
pycolors_kit-1.0.4.dist-info/WHEEL
pycolors_kit-1.0.4.dist-info/top_level.txt
pycolors_kit-1.0.4.dist-info/zip-safe
pycolors_kit-1.0.4.dist-info/RECORD
