Metadata-Version: 2.1
Name: pycolors-kit
Version: 1.0.4
Summary: Search for color names through HEX, or search for color information through names
Home-page: https://github.com/game4d/pycolors-kit
Author: game4d
Author-email: game4d@163.com
License: MIT Licence
Platform: any
Classifier: Programming Language :: Python :: 3
Classifier: License :: OSI Approved :: MIT License
Classifier: Operating System :: OS Independent
Requires-Dist: numpy
